monotome/__init__.py
monotome/cli.py
monotome/graph.py
monotome/migrations.py
monotome/tracking.py
monotome-0.2.0.dist-info/LICENSE
monotome-0.2.0.dist-info/METADATA
monotome-0.2.0.dist-info/WHEEL
monotome-0.2.0.dist-info/entry_points.txt
monotome-0.2.0.dist-info/RECORD
